companieshouse.py
companies_house_api_lib-0.2.dist-info/licenses/LICENSE
companies_house_api_lib-0.2.dist-info/METADATA
companies_house_api_lib-0.2.dist-info/WHEEL
companies_house_api_lib-0.2.dist-info/top_level.txt
companies_house_api_lib-0.2.dist-info/RECORD
