Metadata-Version: 2.4
Name: companies-house-api-lib
Version: 0.2
Summary: A Python client for the Companies House API
Home-page: https://github.com/aagardezi/companies-house-api-lib
Author: Ali Gardezi
Author-email: aagardezi+github@gmail.com
Classifier: Programming Language :: Python :: 3
Classifier: License :: OSI Approved :: MIT License
Classifier: Operating System :: OS Independent
License-File: LICENSE
Requires-Dist: requests
Dynamic: author
Dynamic: author-email
Dynamic: classifier
Dynamic: description
Dynamic: description-content-type
Dynamic: home-page
Dynamic: license-file
Dynamic: requires-dist
Dynamic: summary
